blitskrieg/__init__.py
blitskrieg/bitcoin.py
blitskrieg/bli.py
blitskrieg/blitskrieg.proto
blitskrieg/blitskrieg.py
blitskrieg/blitskrieg_pb2.py
blitskrieg/blitskrieg_pb2_grpc.py
blitskrieg/lightning.py
blitskrieg/settings.py
blitskrieg/share/complete-bli.bash
blitskrieg/share/complete-bli.zsh
blitskrieg/share/config.sample
blitskrieg/share/init_electrum.sh
blitskrieg/utils/__init__.py
blitskrieg/utils/bitcoin.py
blitskrieg/utils/blitskrieg.py
blitskrieg/utils/common.py
blitskrieg/utils/configure_stack.py
blitskrieg/utils/exceptions.py
blitskrieg/utils/lightning.py
blitskrieg-0.2.1.dist-info/entry_points.txt
blitskrieg-0.2.1.dist-info/COPYING
blitskrieg-0.2.1.dist-info/WHEEL
blitskrieg-0.2.1.dist-info/METADATA
blitskrieg-0.2.1.dist-info/RECORD
