Metadata-Version: 2.1
Name: blitskrieg
Version: 0.2.1
Summary: The Bitcoin Lightning Integration Test Service
Home-page: https://gitlab.com/hashbeam/blitskrieg
License: AGPL-3.0-or-later
Keywords: ln,lightning network,bitcoin,integration,test,boltlight
Author: Hashbeam
Author-email: hashbeam@protonmail.com
Requires-Python: >=3.9.0,<4.0.0
Classifier: Development Status :: 4 - Beta
Classifier: Intended Audience :: Developers
Classifier: License :: OSI Approved :: GNU Affero General Public License v3 or later (AGPLv3+)
Classifier: Natural Language :: English
Classifier: Operating System :: MacOS
Classifier: Operating System :: POSIX :: Linux
Classifier: Programming Language :: Python :: 3
Classifier: Programming Language :: Python :: 3.10
Classifier: Programming Language :: Python :: 3.9
Classifier: Topic :: Other/Nonlisted Topic
Requires-Dist: PyYAML (>=5.4.1,<6.0.0)
Requires-Dist: boltlight-proto (>=2.0.0,<3.0.0)
Requires-Dist: click (>=8.0.4,<9.0.0)
Requires-Dist: docker (>=5.0.3,<6.0.0)
Requires-Dist: docker-compose (>=1.28.5,<2.0.0)
Requires-Dist: googleapis-common-protos (>=1.53.0,<2.0.0)
Requires-Dist: grpcio (>=1.43.0,<2.0.0)
Requires-Dist: protobuf (>=3.19.1,<4.0.0)
Requires-Dist: requests (>=2.25.1,<3.0.0)
Project-URL: Repository, https://gitlab.com/hashbeam/blitskrieg
